auditlog/__init__.py
auditlog/admin.py
auditlog/apps.py
auditlog/cid.py
auditlog/conf.py
auditlog/context.py
auditlog/diff.py
auditlog/filters.py
auditlog/middleware.py
auditlog/mixins.py
auditlog/models.py
auditlog/receivers.py
auditlog/registry.py
auditlog/render.py
auditlog/signals.py
auditlog/locale/ja/LC_MESSAGES/django.mo
auditlog/locale/ja/LC_MESSAGES/django.po
auditlog/locale/ko/LC_MESSAGES/django.mo
auditlog/locale/ko/LC_MESSAGES/django.po
auditlog/management/__init__.py
auditlog/management/commands/__init__.py
auditlog/management/commands/auditlogflush.py
auditlog/management/commands/auditlogmigratejson.py
auditlog/migrations/0001_initial.py
auditlog/migrations/0002_auto_support_long_primary_keys.py
auditlog/migrations/0003_logentry_remote_addr.py
auditlog/migrations/0004_logentry_detailed_object_repr.py
auditlog/migrations/0005_logentry_additional_data_verbose_name.py
auditlog/migrations/0006_object_pk_index.py
auditlog/migrations/0007_object_pk_type.py
auditlog/migrations/0008_action_index.py
auditlog/migrations/0009_alter_logentry_additional_data.py
auditlog/migrations/0010_alter_logentry_timestamp.py
auditlog/migrations/0011_logentry_serialized_data.py
auditlog/migrations/0012_add_logentry_action_access.py
auditlog/migrations/0013_alter_logentry_timestamp.py
auditlog/migrations/0014_logentry_cid.py
auditlog/migrations/0015_alter_logentry_changes.py
auditlog/migrations/0016_logentry_remote_port.py
auditlog/migrations/0017_add_actor_email.py
auditlog/migrations/__init__.py
auditlog/templates/auditlog/entry_detail.html
auditlog/templates/auditlog/object_history.html
auditlog/templates/auditlog/pagination.html
auditlog/templatetags/__init__.py
auditlog/templatetags/auditlog_tags.py
django_auditlog-3.4.0.dist-info/LICENSE
django_auditlog-3.4.0.dist-info/METADATA
django_auditlog-3.4.0.dist-info/WHEEL
django_auditlog-3.4.0.dist-info/top_level.txt
django_auditlog-3.4.0.dist-info/RECORD
