Metadata-Version: 2.1
Name: django-auditlog
Version: 3.4.0
Summary: Audit log app for Django
Home-page: https://github.com/jazzband/django-auditlog
Author: Jan-Jelle Kester
License: MIT
Project-URL: Documentation, https://django-auditlog.readthedocs.io
Project-URL: Source, https://github.com/jazzband/django-auditlog
Project-URL: Tracker, https://github.com/jazzband/django-auditlog/issues
Classifier: Programming Language :: Python :: 3
Classifier: Programming Language :: Python :: 3.10
Classifier: Programming Language :: Python :: 3.11
Classifier: Programming Language :: Python :: 3.12
Classifier: Programming Language :: Python :: 3.13
Classifier: Framework :: Django
Classifier: Framework :: Django :: 4.2
Classifier: Framework :: Django :: 5.0
Classifier: Framework :: Django :: 5.1
Classifier: Framework :: Django :: 5.2
Classifier: License :: OSI Approved :: MIT License
Requires-Python: >=3.10
License-File: LICENSE
Requires-Dist: Django>=4.2
Requires-Dist: python-dateutil>=2.7.0
